{
	"BASE_INTERNAL_ERROR": {
		"code": -32603,
		"message": "An internal error occured. Please, try doing this request a few times more or just leave it as is and continue it later",
		"name": "BASE_INTERNAL_ERROR"
	},
	"BASE_INVALID_ARGS": {
		"code": -32602,
		"message": "Invalid params",
		"name": "BASE_INVALID_ARGS"
	},
	"BASE_METHOD_NOT_FOUND": {
		"code": -32601,
		"message": "Method not found",
		"name": "BASE_METHOD_NOT_FOUND"
	},
	"BASE_METHOD_OVERLOAD_NOT_FOUND": {
		"code": -32602,
		"message": "Cannot find suitable method overload. Please, check the args you've passed",
		"name": "BASE_METHOD_OVERLOAD_NOT_FOUND"
	},
	"BALANCE_NOT_ENOUGH": {
		"code": -33010,
		"message": "Not enough balance",
		"name": "BALANCE_NOT_ENOUGH"
	},
	"BOT_INACTIVE": {
		"code": -34300,
		"message": "Bot is inactive",
		"name": "BOT_INACTIVE"
	},
	"BOT_IS_ACTIVE": {
		"code": -34200,
		"message": "Bot is active",
		"name": "BOT_IS_ACTIVE"
	},
	"BOT_NOT_FOUND": {
		"code": -34100,
		"message": "Bot not found",
		"name": "BOT_NOT_FOUND"
	},
	"BOT_ORDER_INVALID": {
		"code": -34020,
		"message": "Invalid order",
		"name": "BOT_ORDER_INVALID"
	},
	"BOT_ORDERS_NOT_FOUND": {
		"code": -34030,
		"message": "Bot orders not found",
		"name": "BOT_ORDERS_NOT_FOUND"
	},
	"BOT_LAP_FINISHED": {
		"code": -34040,
		"message": "Bot lap finished",
		"name": "BOT_LAP_FINISHED"
	},
	"DATA_EMPTY": {
		"code": -35200,
		"message": "Data empty",
		"name": "DATA_EMPTY"
	},
	"DATA_EXISTS": {
		"code": -35030,
		"message": "Data exists",
		"name": "DATA_EXISTS"
	},
	"DATA_HANDLE_ERR": {
		"code": -35001,
		"message": "Data handle error",
		"name": "DATA_HANDLE_ERR"
	},
	"DATA_INVALID": {
		"code": -35100,
		"message": "Invalid data",
		"name": "DATA_INVALID"
	},
	"DATA_NOT_FOUND": {
		"code": -35010,
		"message": "Data not found",
		"name": "DATA_NOT_FOUND"
	},
	"DATA_NO_ACCESS": {
		"code": -35040,
		"message": "Data no acesss",
		"name": "DATA_NO_ACCESS"
	},
	"DATA_REQ_ERR": {
		"code": -35020,
		"message": "Data request error",
		"name": "DATA_REQ_ERR"
	},
	"DATA_UNKNOWN": {
		"code": -35300,
		"message": "Data unknown",
		"name": "DATA_UNKNOWN"
	},
	"DATA_ENCODE_ERR": {
		"code": -35003,
		"message": "Data encode error",
		"name": "DATA_ENCODE_ERR"
	},
	"DATA_PARSE_ERR": {
		"code": -35002,
		"message": "Data parse error",
		"name": "DATA_PARSE_ERR"
	},
	"USER_CRED_INVALID": {
		"code": -36300,
		"message": "User credentials invalid",
		"name": "USER_CRED_INVALID"
	},
	"USER_DELETED": {
		"code": -36001,
		"message": "User deleted",
		"name": "USER_DELETED"
	},
	"USER_EMAIL_ACTIVATION_CODE_WRONG": {
		"code": -36304,
		"message": "Can't find such e-mail activaton code",
		"name": "USER_EMAIL_ACTIVATION_CODE_WRONG"
	},
	"USER_EMAIL_INVALID": {
		"code": -36301,
		"message": "Email is invalid. Please, check its format",
		"name": "USER_EMAIL_INVALID"
	},
	"USER_EMAIL_NOT_IN_WHITELIST": {
		"code": -36303,
		"message": "Now we're at testing stage and your email isn't in whitelist. We can't allow you to register. Sorry",
		"name": "USER_EMAIL_NOT_IN_WHITELIST"
	},
	"USER_EMAIL_RECOVERY_CODE_WRONG": {
		"code": -36305,
		"message": "Can't find such e-mail recovery code",
		"name": "USER_EMAIL_RECOVERY_CODE_WRONG"
	},
	"USER_EMAIL_USED": {
		"code": -36302,
		"message": "This email is already used",
		"name": "USER_EMAIL_USED"
	},
	"USER_IS_AUTH": {
		"code": -36100,
		"message": "User is authorized",
		"name": "USER_IS_AUTH"
	},
	"USER_NOT_AUTH": {
		"code": -36200,
		"message": "User not authorized",
		"name": "USER_NOT_AUTH"
	},
	"USER_NOT_FOUND": {
		"code": -36010,
		"message": "User not found",
		"name": "USER_NOT_FOUND"
	},
	"USER_STATUS_INVALID": {
		"code": -36020,
		"message": "User status invalid",
		"name": "USER_STATUS_INVALID"
	},
	"SERVICE_DISCONNECTED": {
		"code": -37100,
		"message": "Service disconnected",
		"name": "SERVICE_DISCONNECTED"
	},
	"SERVICE_REQ_FAILED": {
		"code": -37010,
		"message": "Service request failed",
		"name": "SERVICE_REQ_FAILED"
	},
	"SERVICE_NO_ACCESS": {
		"code": -37020,
		"message": "No access",
		"name": "SERVICE_NO_ACCESS"
	},
	"SERVICE_CONN_ERR": {
		"code": -37200,
		"message": "Failed to connect to the service",
		"name": "SERVICE_CONN_ERR"
	},
	"SERVICE_REQ_TIMEOUT": {
		"code": -37300,
		"message": "Service request timeout",
		"name": "SERVICE_REQ_TIMEOUT"
	},
	"NOTIFICATIONS_CONFIG_ERROR": {
		"code": -38010,
		"message": "Error configuring notifications",
		"name": "NOTIFICATIONS_CONFIG_ERROR"
	},
	"NOTIFICATIONS_SAVE_EMAIL_ERROR": {
		"code": -38020,
		"message": "Error saving email for notifications",
		"name": "NOTIFICATIONS_SAVE_EMAIL_ERROR"
	},
	"NOTIFICATIONS_TELEGRAM_AUTH_ERROR": {
		"code": -38000,
		"message": "Telegram user authentication error",
		"name": "NOTIFICATIONS_TELEGRAM_AUTH_ERROR"
	},
	"TASK_HANDLE_ERR": {
		"code": -39100,
		"message": "Task processing error",
		"name": "TASK_HANDLE_ERR"
	},
	"STRATEGY_START_MESSAGE_VALIDATION_ERR": {
		"code": -40100,
		"message": "Exception validating strategy start message",
		"name": "STRATEGY_START_MESSAGE_VALIDATION_ERR"
	},
	"STRATEGY_STOP_MESSAGE_VALIDATION_ERR": {
		"code": -40101,
		"message": "Exception validating strategy stop message",
		"name": "STRATEGY_STOP_MESSAGE_VALIDATION_ERR"
	},
	"STRATEGY_NOT_FOUND": {
		"code": -40404,
		"message": "Strategy not found with parameters",
		"name": "STRATEGY_NOT_FOUND"
	},
	"FORMULA_VALIDATION_ERR": {
		"code": -40102,
		"message": "Exception validating formula",
		"name": "FORMULA_VALIDATION_ERR"
	}
}
